cjdns/__init__.py
cjdns/admin_tools.py
cjdns/base32.py
cjdns/bencode.py
cjdns/cjdns.py
cjdns/key_utils.py
cjdns-0.2.4.data/scripts/cexec
cjdns-0.2.4.data/scripts/peerStats
cjdns-0.2.4.dist-info/DESCRIPTION.rst
cjdns-0.2.4.dist-info/METADATA
cjdns-0.2.4.dist-info/RECORD
cjdns-0.2.4.dist-info/WHEEL
cjdns-0.2.4.dist-info/metadata.json
cjdns-0.2.4.dist-info/top_level.txt
