Metadata-Version: 1.1
Name: cjdns
Version: 0.2.4
Summary: A library to interact with the cjdns Admin Interface
Home-page: https://github.com/hyperboria/python-cjdns
Author: Finn Herzfeld
Author-email: finn@seattlemesh.net
License: GPLv3
Keywords: cjdns
Platform: UNKNOWN
Classifier: Development Status :: 3 - Alpha
Classifier: License :: OSI Approved :: GNU Affero General Public License v3
Classifier: Topic :: System :: Networking
